Metadata-Version: 2.1
Name: avhardware
Version: 0.1.4
Summary: PyAV extension with hardware decoding support.
Author: Matteo Destro
Project-URL: Repository, https://github.com/materight/PyAV-Hardware.git
License-File: LICENSE
Requires-Dist: av>=2.3.0
Requires-Dist: torch
